_foo.cpython-36m-x86_64-linux-gnu.so
paddle/_C_ops.py
paddle/__init__.py
paddle/_legacy_C_ops.py
paddle/batch.py
paddle/callbacks.py
paddle/check_import_scipy.py
paddle/common_ops_import.py
paddle/compat.py
paddle/cuda_env.py
paddle/fft.py
paddle/hub.py
paddle/linalg.py
paddle/regularizer.py
paddle/signal.py
paddle/sysconfig.py
paddle/amp/__init__.py
paddle/amp/auto_cast.py
paddle/amp/grad_scaler.py
paddle/audio/__init__.py
paddle/audio/backends/__init__.py
paddle/audio/backends/backend.py
paddle/audio/backends/init_backend.py
paddle/audio/backends/wave_backend.py
paddle/audio/datasets/__init__.py
paddle/audio/datasets/dataset.py
paddle/audio/datasets/esc50.py
paddle/audio/datasets/tess.py
paddle/audio/features/__init__.py
paddle/audio/features/layers.py
paddle/audio/functional/__init__.py
paddle/audio/functional/functional.py
paddle/audio/functional/window.py
paddle/autograd/__init__.py
paddle/autograd/backward_mode.py
paddle/autograd/py_layer.py
paddle/cost_model/__init__.py
paddle/cost_model/cost_model.py
paddle/cost_model/static_op_benchmark.json
paddle/dataset/__init__.py
paddle/dataset/cifar.py
paddle/dataset/common.py
paddle/dataset/conll05.py
paddle/dataset/flowers.py
paddle/dataset/image.py
paddle/dataset/imdb.py
paddle/dataset/imikolov.py
paddle/dataset/mnist.py
paddle/dataset/movielens.py
paddle/dataset/uci_housing.py
paddle/dataset/voc2012.py
paddle/dataset/wmt14.py
paddle/dataset/wmt16.py
paddle/device/__init__.py
paddle/device/cuda/__init__.py
paddle/device/cuda/graphs.py
paddle/device/cuda/streams.py
paddle/distributed/__init__.py
paddle/distributed/cloud_utils.py
paddle/distributed/collective.py
paddle/distributed/elastic.py
paddle/distributed/entry_attr.py
paddle/distributed/parallel.py
paddle/distributed/parallel_with_gloo.py
paddle/distributed/spawn.py
paddle/distributed/auto_parallel/__init__.py
paddle/distributed/auto_parallel/callbacks.py
paddle/distributed/auto_parallel/cluster.py
paddle/distributed/auto_parallel/cluster_v2.py
paddlepaddle-2.4.2.dist-info/LICENSE
paddlepaddle-2.4.2.dist-info/METADATA
paddlepaddle-2.4.2.dist-info/WHEEL
paddlepaddle-2.4.2.dist-info/entry_points.txt
paddlepaddle-2.4.2.dist-info/top_level.txt
paddlepaddle-2.4.2.dist-info/RECORD
